combined_energy/__init__.py
combined_energy/client.py
combined_energy/constants.py
combined_energy/exceptions.py
combined_energy/helpers.py
combined_energy/models.py
combined_energy/utils.py
combined_energy_api-1.0.1.dist-info/LICENSE
combined_energy_api-1.0.1.dist-info/METADATA
combined_energy_api-1.0.1.dist-info/WHEEL
combined_energy_api-1.0.1.dist-info/RECORD
