Metadata-Version: 2.3
Name: combined-energy-api
Version: 1.0.1
Summary: Python interface to the Combined Energy API
License: BSD-3-Clause
Keywords: energy,monitoring,combined.energy,api,client,async
Author: Tim Savage
Author-email: tim@savage.company
Maintainer: Tim Savage
Maintainer-email: tim@savage.company
Requires-Python: >=3.11,<4.0
Classifier: Development Status :: 4 - Beta
Classifier: Intended Audience :: Developers
Classifier: License :: OSI Approved :: BSD License
Classifier: Operating System :: OS Independent
Classifier: Programming Language :: Python
Classifier: Programming Language :: Python :: 3
Classifier: Programming Language :: Python :: 3.11
Classifier: Programming Language :: Python :: 3.12
Classifier: Programming Language :: Python :: 3.13
Classifier: Topic :: Software Development :: Libraries :: Python Modules
Requires-Dist: aiohttp
Requires-Dist: async-timeout ; python_version < "3.11"
Requires-Dist: pydantic (>=2.0,<3.0)
Project-URL: Documentation, https://github.com/timsavage/combined-energy-api
Project-URL: Homepage, https://github.com/timsavage/combined-energy-api
Project-URL: Repository, https://github.com/timsavage/combined-energy-api
